pykuda2/__init__.py
pykuda2/base.py
pykuda2/exceptions.py
pykuda2/kuda.py
pykuda2/utils.py
pykuda2/wrappers/__init__.py
pykuda2/wrappers/async_wrappers/__init__.py
pykuda2/wrappers/async_wrappers/accounts.py
pykuda2/wrappers/async_wrappers/billing_and_betting.py
pykuda2/wrappers/async_wrappers/card.py
pykuda2/wrappers/async_wrappers/gift_card.py
pykuda2/wrappers/async_wrappers/instant_settlement_service.py
pykuda2/wrappers/async_wrappers/savings.py
pykuda2/wrappers/async_wrappers/transaction.py
pykuda2/wrappers/sync_wrappers/__init__.py
pykuda2/wrappers/sync_wrappers/accounts.py
pykuda2/wrappers/sync_wrappers/billing_and_betting.py
pykuda2/wrappers/sync_wrappers/card.py
pykuda2/wrappers/sync_wrappers/gift_card.py
pykuda2/wrappers/sync_wrappers/instant_settlement_service.py
pykuda2/wrappers/sync_wrappers/savings.py
pykuda2/wrappers/sync_wrappers/transaction.py
pykuda2-0.1.2.dist-info/LICENSE
pykuda2-0.1.2.dist-info/METADATA
pykuda2-0.1.2.dist-info/WHEEL
pykuda2-0.1.2.dist-info/RECORD
